unlock_processpool/__init__.py
unlock_processpool/core.py
unlock_processpool_win-2.3.0.dist-info/METADATA
unlock_processpool_win-2.3.0.dist-info/WHEEL
unlock_processpool_win-2.3.0.dist-info/top_level.txt
unlock_processpool_win-2.3.0.dist-info/RECORD
