Metadata-Version: 2.1
Name: unlock-processpool-win
Version: 2.3.0
Summary: Unlock Windows process limit for ProcessPoolExecutor and joblib (61->2046 workers)
Home-page: https://github.com/JackLFH/unlock-processpool
Author: Half open flowers
Author-email: Half open flowers <1816524875@qq.com>
License: BSD-3-Clause
Project-URL: Homepage, https://github.com/JackLFH/unlock-processpool
Classifier: Programming Language :: Python :: 3
Classifier: License :: OSI Approved :: BSD License
Classifier: Operating System :: Microsoft :: Windows
Requires-Python: >=3.8
